rlsa.cpython-39-x86_64-linux-gnu.so
rlsa/rlsa.c
rlsa-0.0.2.dist-info/top_level.txt
rlsa-0.0.2.dist-info/METADATA
rlsa-0.0.2.dist-info/WHEEL
rlsa-0.0.2.dist-info/LICENSE
rlsa-0.0.2.dist-info/RECORD
