Metadata-Version: 2.1
Name: rlsa
Version: 0.0.2
Summary: Run Length Smoothing Algorithm
Home-page: https://github.com/hoel-bagard/rlsa
Author: Hoel Bagard
License: UNKNOWN
Keywords: rlsa
Platform: UNKNOWN
Classifier: License :: OSI Approved :: MIT License
Classifier: Programming Language :: Python :: 3
Classifier: Programming Language :: Python :: 3.8
Classifier: Programming Language :: Python :: 3.9
Classifier: Programming Language :: Python :: 3.10
Requires-Python: >=3.8
License-File: LICENSE
Requires-Dist: numpy
